{
	"ignore": {
		"Audio": [
			"alternate_group",
			"codec_id_info",
			"codec_id_url",
			"count",
			"count_of_stream_of_this_kind",
			"default",
			"description_of_the_codec",
			"firstpacketorder",
			"format_info",
			"format_url",
			"kind_of_stream",
			"menu_id",
			"menus",
			"other_alignment",
			"other_alternate_group",
			"other_bed_channel_count",
			"other_bit_depth",
			"other_bit_rate",
			"other_bit_rate_mode",
			"other_channel_positions",
			"other_channel_s",
			"other_channel_s__original",
			"other_commercial_name",
			"other_compr",
			"other_compr_average",
			"other_compr_maximum",
			"other_compr_minimum",
			"other_compression_mode",
			"other_default",
			"other_delay",
			"other_delay__origin",
			"other_delay_relative_to_video",
			"other_detected_bit_depth",
			"other_dialnorm_average",
			"other_dialnorm_maximum",
			"other_dialnorm_minimum",
			"other_dialog_normalization",
			"other_dsurmod",
			"other_duration",
			"other_duration_firstframe",
			"other_duration_lastframe",
			"other_dynrng",
			"other_dynrng_average",
			"other_dynrng_maximum",
			"other_dynrng_minimum",
			"other_forced",
			"other_format",
			"other_format_settings__ps",
			"other_format_settings__sbr",
			"other_frame_rate",
			"other_id_in_the_original_source_medium",
			"other_interleave__duration",
			"other_interleave__preload_duration",
			"other_kind_of_stream",
			"other_language",
			"other_maximum_bit_rate",
			"other_menu_id",
			"other_minimum_bit_rate",
			"other_nominal_bit_rate",
			"other_replay_gain",
			"other_sampling_rate",
			"other_service_kind",
			"other_source_duration",
			"other_source_duration_firstframe",
			"other_source_duration_lastframe",
			"other_source_stream_size",
			"other_stream_identifier",
			"other_stream_size",
			"other_track_id",
			"other_writing_application",
			"other_writing_library",
			"proportion_of_this_stream",
			"source_streamsize_proportion",
			"stream_identifier",
			"streamorder",
			"track_id",
			"track_type"
		],
		"General": [
			"audio_codecs",
			"audio_format_list",
			"audio_format_withhint_list",
			"audio_language_list",
			"bytelength",
			"codec_id_url",
			"codecid_compatible",
			"codecs_video",
			"complete_name",
			"completename_last",
			"count",
			"count_of_audio_streams",
			"count_of_image_streams",
			"count_of_menu_streams",
			"count_of_stream_of_this_kind",
			"count_of_text_streams",
			"count_of_video_streams",
			"file_creation_date",
			"file_creation_date__local",
			"file_extension",
			"file_last_modification_date",
			"file_last_modification_date__local",
			"file_name",
			"file_name_extension",
			"file_size",
			"fileextension_last",
			"filename_last",
			"filenameextension_last",
			"filesize",
			"folder_name",
			"foldername_last",
			"format_extensions_usually_used",
			"format_info",
			"format_url",
			"frame_count",
			"frame_rate",
			"hasaudio",
			"hasimage",
			"hasscript",
			"hasvideo",
			"image_format_list",
			"image_format_withhint_list",
			"kind_of_stream",
			"menu_codecs",
			"menu_format_list",
			"menu_format_withhint_list",
			"menu_language_list",
			"original_filename",
			"other_album",
			"other_album_replay_gain",
			"other_codec_id",
			"other_codec_list",
			"other_comment",
			"other_commercial_name",
			"other_compilation",
			"other_copyright",
			"other_delay",
			"other_duration",
			"other_file_size",
			"other_format",
			"other_format_list",
			"other_format_withhint_list",
			"other_frame_rate",
			"other_kind_of_stream",
			"other_language_list",
			"other_maximum_overall_bit_rate",
			"other_musicbrainz_discid",
			"other_original_album",
			"other_overall_bit_rate",
			"other_overall_bit_rate_mode",
			"other_performer",
			"other_producer",
			"other_stream_size",
			"other_title",
			"other_track_id",
			"other_unique_id",
			"other_unknown",
			"other_writing_application",
			"other_writing_library",
			"othercount",
			"overall_bit_rate_mode",
			"proportion_of_this_stream",
			"size",
			"stream_identifier",
			"text_codecs",
			"text_format_list",
			"text_format_withhint_list",
			"text_language_list",
			"track_id",
			"track_type",
			"video_format_list",
			"video_format_withhint_list",
			"video_language_list"
		],
		"Image": [
			"count",
			"count_of_stream_of_this_kind",
			"format_info",
			"kind_of_stream",
			"other_bit_depth",
			"other_compression_mode",
			"other_display_aspect_ratio",
			"other_format",
			"other_height",
			"other_kind_of_stream",
			"other_stream_size",
			"other_width",
			"proportion_of_this_stream",
			"stream_identifier",
			"track_type"
		],
		"Menu": [
			"count",
			"count_of_stream_of_this_kind",
			"kind_of_stream",
			"other_kind_of_stream",
			"stream_identifier",
			"track_type"
		],
		"Other": [
			"count",
			"count_of_stream_of_this_kind",
			"default",
			"kind_of_stream",
			"other_bit_rate_mode",
			"other_default",
			"other_duration",
			"other_format",
			"other_frame_rate",
			"other_kind_of_stream",
			"other_language",
			"other_source_duration",
			"other_source_duration_lastframe",
			"other_source_stream_size",
			"other_stream_identifier",
			"other_stream_size",
			"other_time_code__striped",
			"other_track_id",
			"stream_identifier",
			"streamorder",
			"track_id",
			"track_type"
		],
		"Text": [
			"codec_id_info",
			"codec_id_url",
			"count",
			"count_of_stream_of_this_kind",
			"default",
			"firstpacketorder",
			"format_info",
			"format_url",
			"kind_of_stream",
			"menu_id",
			"other_alternate_group",
			"other_bit_rate",
			"other_bit_rate_mode",
			"other_compression_mode",
			"other_default",
			"other_delay",
			"other_delay__origin",
			"other_delay_relative_to_video",
			"other_duration",
			"other_forced",
			"other_format",
			"other_frame_rate",
			"other_id_in_the_original_source_medium",
			"other_kind_of_stream",
			"other_language",
			"other_maximum_bit_rate",
			"other_menu_id",
			"other_stream_identifier",
			"other_stream_size",
			"other_track_id",
			"proportion_of_this_stream",
			"stream_identifier",
			"streamorder",
			"track_id",
			"track_type"
		],
		"Video": [
			"codec_id_info",
			"codec_id_url",
			"count",
			"count_of_stream_of_this_kind",
			"default",
			"description_of_the_codec",
			"firstpacketorder",
			"format_info",
			"format_url",
			"hdr_format_compatibility",
			"kind_of_stream",
			"menu_id",
			"menus",
			"other_active_format_description",
			"other_bit_depth",
			"other_bit_rate",
			"other_bit_rate_mode",
			"other_chroma_subsampling",
			"other_clean_aperture_display_aspect_ratio",
			"other_clean_aperture_height",
			"other_clean_aperture_width",
			"other_commercial_name",
			"other_compression_mode",
			"other_default",
			"other_delay",
			"other_delay__origin",
			"other_delay_original",
			"other_display_aspect_ratio",
			"other_duration",
			"other_duration_firstframe",
			"other_duration_lastframe",
			"other_encoded_bit_rate",
			"other_forced",
			"other_format",
			"other_format_settings__bvop",
			"other_format_settings__cabac",
			"other_format_settings__gmc",
			"other_format_settings__matrix",
			"other_format_settings__qpel",
			"other_format_settings__reference_frames",
			"other_frame_rate",
			"other_frame_rate_mode",
			"other_gop__open_closed",
			"other_gop__open_closed_of_first_frame",
			"other_hdr_format",
			"other_height",
			"other_height_offset",
			"other_id_in_the_original_source_medium",
			"other_kind_of_stream",
			"other_language",
			"other_maximum_bit_rate",
			"other_maximum_frame_rate",
			"other_menu_id",
			"other_minimum_frame_rate",
			"other_nominal_bit_rate",
			"other_nominal_frame_rate",
			"other_original_display_aspect_ratio",
			"other_original_frame_rate",
			"other_original_height",
			"other_original_scan_order",
			"other_original_scan_type",
			"other_original_width",
			"other_rotation",
			"other_scan_order",
			"other_scan_type",
			"other_scan_type__store_method",
			"other_source_duration",
			"other_source_duration_firstframe",
			"other_source_duration_lastframe",
			"other_source_stream_size",
			"other_stream_identifier",
			"other_stream_size",
			"other_track_id",
			"other_width",
			"other_width_offset",
			"other_writing_library",
			"proportion_of_this_stream",
			"source_streamsize_proportion",
			"stream_identifier",
			"streamorder",
			"track_id",
			"track_type"
		]
	},
	"use": {
		"Audio": [
			"acmod",
			"alignment",
			"averagelevel",
			"bed_channel_configuration",
			"bed_channel_count",
			"bit_depth",
			"bit_rate",
			"bit_rate_mode",
			"bps",
			"bsid",
			"channel_layout",
			"channel_positions",
			"channel_s",
			"channel_s__original",
			"channellayout_original",
			"channelpositions_original",
			"codec_id",
			"codec_id_hint",
			"commercial_name",
			"complexity_index",
			"compr",
			"compr_average",
			"compr_count",
			"compr_maximum",
			"compr_minimum",
			"compression_mode",
			"delay",
			"delay__origin",
			"delay_dropframe",
			"delay_relative_to_video",
			"description",
			"detected_bit_depth",
			"dialnorm_average",
			"dialnorm_count",
			"dialnorm_maximum",
			"dialnorm_minimum",
			"dialog_normalization",
			"dsurmod",
			"duration",
			"duration_firstframe",
			"duration_lastframe",
			"duration_source",
			"dynrng",
			"dynrng_average",
			"dynrng_count",
			"dynrng_maximum",
			"dynrng_minimum",
			"emphasis",
			"encoded_application_url",
			"encoded_date",
			"encoded_library_date",
			"encoded_library_name",
			"encoded_library_version",
			"encoding_info",
			"encoding_settings",
			"encryption",
			"forced",
			"format",
			"format_additionalfeatures",
			"format_identifier",
			"format_profile",
			"format_settings",
			"format_settings__endianness",
			"format_settings__firm",
			"format_settings__floor",
			"format_settings__ps",
			"format_settings__sbr",
			"format_settings__sign",
			"format_version",
			"frame_count",
			"frame_rate",
			"fromstats_bitrate",
			"fromstats_duration",
			"fromstats_framecount",
			"fromstats_streamsize",
			"genre",
			"id_in_the_original_source_medium",
			"interleave__duration",
			"interleave__preload_duration",
			"internet_media_type",
			"language",
			"lfeon",
			"maximum_bit_rate",
			"mdhd_duration",
			"minimum_bit_rate",
			"mode",
			"mode_extension",
			"mp3gain__min_max",
			"muxing_mode",
			"nominal_bit_rate",
			"number_of_dynamic_objects",
			"numberofframes",
			"original_source_medium",
			"peakvalue",
			"performer",
			"replay_gain",
			"replay_gain_peak",
			"samples_count",
			"samples_per_frame",
			"sampling_rate",
			"samplingcount_source",
			"service_kind",
			"source_delay",
			"source_delay_source",
			"source_duration",
			"source_duration_firstframe",
			"source_duration_lastframe",
			"source_frame_count",
			"source_stream_size",
			"statistics_tags_issue",
			"stream_size",
			"tagged_date",
			"title",
			"track_position",
			"undo",
			"unique_id",
			"writing_application",
			"writing_library"
		],
		"General": [
			"accompaniment",
			"accurateripcount",
			"accurateripcountalloffsets",
			"accurateripcountwithoffset",
			"accurateripcrc",
			"accurateripdiscid",
			"accurateripid",
			"accurateripoffset",
			"accurateripresult",
			"accurateriptotal",
			"acoustid_id",
			"album",
			"album_artist",
			"album_composer",
			"album_dynamic_range",
			"album_group",
			"album_performer",
			"album_performer_sort",
			"album_replay_gain",
			"album_replay_gain_peak",
			"album_sorted_by",
			"albumartist",
			"albumartistsort",
			"albumtitleid",
			"analysis",
			"applestoreaccount",
			"applestoreaccounttype",
			"applestorecatalogid",
			"applestorecountry",
			"application",
			"arranger",
			"artist",
			"artists",
			"artistsort",
			"asin",
			"attachments",
			"audio_converter_home_page",
			"audiodatarate",
			"aurl",
			"author",
			"author_url",
			"auto_converted_from_id3_v11",
			"averagelevel",
			"band",
			"barcode",
			"bext_present",
			"bio",
			"bitrate",
			"bpm",
			"bpm__beats_per_minute",
			"bps",
			"broadcast",
			"can_skip_backward",
			"can_skip_forward",
			"canseekontime",
			"canseektoend",
			"catalog",
			"catalog_number",
			"catalognumber",
			"cddb_disc_id",
			"cddb_discid",
			"cdtoc",
			"chorus",
			"codec_id",
			"codecid_version",
			"codecs_image",
			"codirector",
			"collection",
			"comandroidversion",
			"comapplequicktimeartwork",
			"comapplequicktimeauthor",
			"comapplequicktimecontentidentifier",
			"comapplequicktimecreationdate",
			"comapplequicktimeismontage",
			"comapplequicktimekeywords",
			"comapplequicktimelocationaccuracyhorizontal",
			"comapplequicktimelocationiso6709",
			"comapplequicktimemake",
			"comapplequicktimemodel",
			"comapplequicktimeplayermovieaudiomute",
			"comapplequicktimesoftware",
			"comapplequicktimetitle",
			"comment",
			"comments",
			"commercial_information",
			"commercial_name",
			"comnexvio8mm",
			"comnexvio8mmfilm",
			"comnexvio8mmfilmid",
			"comnexvio8mmlensid",
			"comnexvio8mmthumbnail",
			"compatible_brands",
			"compilation",
			"composer",
			"composer_sorted_by",
			"composersort",
			"conductor",
			"content_group_description",
			"contentgroup",
			"contenttype",
			"contributing_artist",
			"converter",
			"copyright",
			"copyright_legal_information",
			"copyright_message",
			"copywarning",
			"country",
			"cover",
			"cover_description",
			"cover_mime",
			"cover_type",
			"covers_hq_full",
			"covr",
			"crc_error_pos",
			"creation_time",
			"ctdbdiscconfidence",
			"ctdbtrackconfidence",
			"cue",
			"currentbitrate",
			"d",
			"data",
			"datasize",
			"date",
			"dedication",
			"delay",
			"description",
			"descriptor",
			"deviceconformancetemplate",
			"dew_army",
			"digite_aqui_a_descrio",
			"dimensions",
			"director",
			"discid",
			"discogs_artist_id",
			"discogs_catalog",
			"discogs_country",
			"discogs_label",
			"discogs_label_id",
			"discogs_master_release_id",
			"discogs_rating",
			"discogs_release",
			"discogs_release_id",
			"discogs_released",
			"discogs_votes",
			"discsubtitle",
			"displayheight",
			"displaywidth",
			"download",
			"dummytitle",
			"dummytrack",
			"duration",
			"dvrwindow",
			"dynamic_range",
			"edgeip",
			"edgeversion",
			"encoded_application_companyname",
			"encoded_application_name",
			"encoded_by",
			"encoded_date",
			"encoded_library_name",
			"encoded_library_version",
			"encodedby",
			"encoder",
			"encodersettings",
			"encoding",
			"encoding_info",
			"encoding_params",
			"encoding_settings",
			"eng",
			"engineer",
			"ensemble",
			"errordetectiontype",
			"eventid",
			"file_type",
			"fileextension_invalid",
			"fingerprint",
			"first_played",
			"folgeautor",
			"folgebuch",
			"folgenummer",
			"footersize",
			"format",
			"format_additionalfeatures",
			"format_profile",
			"format_settings",
			"format_version",
			"frameheight",
			"framerate",
			"framewidth",
			"full_name",
			"gattung",
			"genre",
			"genreid",
			"gn_discartist",
			"gracenoteextdata",
			"gracenotefileid",
			"grouping",
			"gshh",
			"gssd",
			"gsst",
			"gstd",
			"hasarbitrarydatastream",
			"hasattachedimages",
			"hasfiletransferstream",
			"headersize",
			"height",
			"helium2_rating",
			"helium_comment",
			"http___wwwjamendocom",
			"httphostheader",
			"id3",
			"id3v1_comment",
			"idfv",
			"ifkeycert",
			"imdb",
			"initial_key",
			"interleaved",
			"internet_media_type",
			"involved_people",
			"irip",
			"is_protected",
			"is_trusted",
			"islive",
			"isrc",
			"isstreamable",
			"istruncated",
			"itunes_cddb_1",
			"itunes_cddb_ids",
			"itunes_cddb_tracknumber",
			"itunnorm",
			"itunpgap",
			"itunsmpb",
			"kategorien",
			"keyword",
			"keywords",
			"label",
			"label_catalog",
			"labelno",
			"language",
			"language_2letter",
			"last_played",
			"law_rating",
			"lead_artist",
			"length",
			"limited_edition",
			"livexml",
			"lmdo",
			"log",
			"logchecker",
			"logfile",
			"lyricist",
			"lyrics",
			"major_brand",
			"make",
			"mastered_date",
			"maximum_overall_bit_rate",
			"mcdi",
			"mcn",
			"media",
			"media_history_uuid",
			"media_jukebox__date",
			"media_jukebox__intensity",
			"media_jukebox__peak_level",
			"media_jukebox__replay_gain",
			"media_jukebox__tool_name",
			"media_jukebox__tool_version",
			"media_type",
			"media_uuid",
			"mediafoundationversion",
			"mediatype",
			"mediumanzahl",
			"mediumid",
			"minor_version",
			"mixer",
			"model",
			"moovposition",
			"movie_more",
			"movie_name",
			"movie_name_url",
			"mp3gain_minmax",
			"mp3infp_ver228a",
			"music_group",
			"musicbrainz_album_artist_id",
			"musicbrainz_album_id",
			"musicbrainz_album_release_country",
			"musicbrainz_album_status",
			"musicbrainz_album_type",
			"musicbrainz_artist_id",
			"musicbrainz_date",
			"musicbrainz_disc_id",
			"musicbrainz_discid",
			"musicbrainz_release_group_id",
			"musicbrainz_release_track_id",
			"musicbrainz_releasegroupid",
			"musicbrainz_releasetrackid",
			"musicbrainz_track_id",
			"musicbrainz_trm_id",
			"musicbrainz_workid",
			"musician_credit_list",
			"musicip_data",
			"musicip_puid",
			"musicmagic_data",
			"musicmagic_fingerprint",
			"musicmatch_trackartist",
			"ncdt",
			"no_description",
			"notes",
			"ocra0017",
			"official_audio_file_webpage",
			"official_audio_source_webpage",
			"optimalbitrate",
			"orchestra",
			"origalbum",
			"origartist",
			"origin_website",
			"original_album",
			"original_lyricist",
			"original_performer",
			"original_release",
			"original_released_date",
			"original_source_form",
			"original_source_form_distributed_by",
			"original_source_form_name",
			"original_source_medium",
			"originaldate",
			"originallanguageartist",
			"originallanguagetitle",
			"originalyear",
			"ost",
			"overall_bit_rate",
			"overallbitrate_precision_max",
			"overallbitrate_precision_min",
			"overlay",
			"part",
			"part_position",
			"part_total",
			"payment",
			"peakvalue",
			"performer",
			"performer_sorted_by",
			"performer_url",
			"play_counter",
			"play_stamp",
			"playerip",
			"podcast",
			"podcast_category",
			"podcasturl",
			"private_totalbitrate",
			"producer",
			"producer_reference",
			"production_studio",
			"provider",
			"publisher",
			"publisher_url",
			"puid",
			"purchasedate",
			"pztageditor_info",
			"rati",
			"rating",
			"rating_wmp",
			"recorded_date",
			"recorded_location",
			"recording_venue",
			"related",
			"release_cat",
			"release_date",
			"release_type",
			"releasecountry",
			"released_date",
			"releasestatus",
			"releasetype",
			"releaseyear",
			"remixed_by",
			"remixedby",
			"replaygain_album_gain",
			"replaygain_album_peak",
			"replaygain_track_gain",
			"replaygain_track_minmax",
			"replaygain_track_peak",
			"replaygain_undo",
			"retail_date",
			"rip_date",
			"ripped_with",
			"ripper",
			"ripping_tool",
			"runtime",
			"script",
			"season",
			"seekable",
			"segm",
			"service_name",
			"service_url",
			"session",
			"set_subtitle",
			"setsubtitle",
			"sforiginalfps",
			"software",
			"software_hardware_and_settings_used_for_encoding",
			"soloists",
			"songrights",
			"songtype",
			"soundjam_cddb_1",
			"soundjam_cddb_tracknumber",
			"source",
			"sourcedata",
			"sourcemedia",
			"starttime",
			"status",
			"stereoscopic",
			"stereoscopiclayout",
			"stereoscopicpreview",
			"stereoscopicskip",
			"stream_size",
			"streamname",
			"streamtype",
			"stridable",
			"style",
			"subject",
			"subtitle",
			"subtracknummer",
			"subtracknummergesamt",
			"summary",
			"supplier",
			"switchfail",
			"tagged_by",
			"tagged_date",
			"tagging_application",
			"tagging_time",
			"tagscanner",
			"tat",
			"tcdo",
			"tchapter",
			"tcod",
			"tdes",
			"tdr",
			"tds",
			"tempo",
			"tgid",
			"thanks_to",
			"thmb",
			"tid",
			"tim",
			"timebase",
			"timeoflasttat",
			"times_played",
			"titel",
			"title",
			"title__more_info",
			"title_sort",
			"title_url",
			"tmdb",
			"tool",
			"tool_name",
			"toolname",
			"toolversion",
			"totaldatarate",
			"totalduration",
			"totaltracks",
			"track_comments",
			"track_itunes_cddb_ids",
			"track_more",
			"track_name",
			"track_name_position",
			"track_name_sorted_by",
			"track_name_total",
			"track_name_url",
			"tracknumber",
			"transfertoken",
			"tsc",
			"tsz",
			"tt3",
			"tvnetworkname",
			"type",
			"type_description_here",
			"ufidhttp___wwwcddbcom_id3_taginfo1html",
			"umid",
			"unique_id",
			"unknown",
			"unsyncedlyrics",
			"upc",
			"uploader",
			"url",
			"user",
			"va_artist",
			"vendor",
			"version",
			"vgmdb",
			"vgmdb_album_url",
			"videodatarate",
			"vocals",
			"web",
			"width",
			"wizistserie",
			"wm_albumartist",
			"wm_albumartistsortorder",
			"wm_artists",
			"wm_barcode",
			"wm_catalogno",
			"wm_codedby",
			"wm_composer",
			"wm_composersortorder",
			"wm_containerformat",
			"wm_encodingsettings",
			"wm_encodingtime",
			"wm_engineer",
			"wm_iscompilation",
			"wm_isrc",
			"wm_itunespodcasturl",
			"wm_lyrics",
			"wm_media",
			"wm_mediaprimaryclassid",
			"wm_mixer",
			"wm_originalartist",
			"wm_originalreleaseyear",
			"wm_partofset",
			"wm_producer",
			"wm_provider",
			"wm_providerrating",
			"wm_publisher",
			"wm_script",
			"wm_setsubtitle",
			"wm_shareduserrating",
			"wm_show",
			"wm_subscriptioncontentid",
			"wm_titlesortorder",
			"wm_url",
			"wm_userweburl",
			"work",
			"writer",
			"writing_application",
			"writing_frontend",
			"writing_library",
			"written_by",
			"www",
			"wwwartist",
			"wwwplayskullcom__wrenchpilot_bigfoot",
			"xtra",
			"xyz",
			"year",
			"ytmnd"
		],
		"Image": [
			"bit_depth",
			"chroma_subsampling",
			"codec_id",
			"color_space",
			"colorspace_icc",
			"commercial_name",
			"compression_mode",
			"density",
			"density_unit",
			"density_x",
			"density_y",
			"display_aspect_ratio",
			"encoded_date",
			"format",
			"format_compression",
			"format_profile",
			"format_settings",
			"format_settings__endianness",
			"height",
			"internet_media_type",
			"method",
			"pixel_aspect_ratio",
			"stream_size",
			"title",
			"width"
		],
		"Menu": [
			"chapters_pos_begin",
			"chapters_pos_end"
		],
		"Other": [
			"bit_rate_mode",
			"codec_id",
			"commercial_name",
			"duration",
			"duration_firstframe",
			"duration_lastframe",
			"encoded_date",
			"format",
			"frame_count",
			"frame_rate",
			"framerate_den",
			"framerate_num",
			"language",
			"mdhd_duration",
			"source_delay",
			"source_delay_source",
			"source_duration",
			"source_duration_lastframe",
			"source_frame_count",
			"source_stream_size",
			"stream_size",
			"tagged_date",
			"time_code__striped",
			"time_code_of_first_frame",
			"title",
			"type"
		],
		"Text": [
			"alternate_group",
			"bit_rate",
			"bit_rate_mode",
			"bps",
			"captionservicename",
			"codec_id",
			"commercial_name",
			"compression_mode",
			"count_of_elements",
			"delay",
			"delay__origin",
			"delay_dropframe",
			"delay_relative_to_video",
			"duration",
			"encoded_date",
			"forced",
			"format",
			"frame_count",
			"frame_rate",
			"fromstats_bitrate",
			"fromstats_duration",
			"fromstats_framecount",
			"fromstats_streamsize",
			"id_in_the_original_source_medium",
			"language",
			"maximum_bit_rate",
			"muxing_mode",
			"muxing_mode__more_info",
			"original_source_medium",
			"statistics_tags_issue",
			"stream_size",
			"tagged_date",
			"title",
			"unique_id"
		],
		"Video": [
			"active_format_description",
			"active_format_description__muxing_mode",
			"bit_depth",
			"bit_rate",
			"bit_rate_mode",
			"bits__pixel_frame",
			"bps",
			"buffer_size",
			"chroma_subsampling",
			"clean_aperture_display_aspect_ratio",
			"clean_aperture_height",
			"clean_aperture_pixel_aspect_ratio",
			"clean_aperture_width",
			"codec_configuration_box",
			"codec_id",
			"codec_id_hint",
			"color_primaries",
			"color_range",
			"color_space",
			"colour_description_present",
			"colour_description_present_source",
			"colour_primaries_original",
			"colour_primaries_original_source",
			"colour_primaries_source",
			"colour_range_original",
			"colour_range_original_source",
			"colour_range_source",
			"commercial_name",
			"compression_mode",
			"data_partitioned",
			"delay",
			"delay__origin",
			"delay_dropframe",
			"delay_original",
			"delay_original_dropframe",
			"delay_original_settings",
			"delay_original_source",
			"delay_settings",
			"display_aspect_ratio",
			"duration",
			"duration_firstframe",
			"duration_lastframe",
			"duration_source",
			"encoded_bit_rate",
			"encoded_date",
			"encoded_library_date",
			"encoded_library_name",
			"encoded_library_version",
			"encoding_info",
			"encoding_settings",
			"encryption",
			"forced",
			"format",
			"format_compression",
			"format_identifier",
			"format_profile",
			"format_settings",
			"format_settings__bvop",
			"format_settings__cabac",
			"format_settings__gmc",
			"format_settings__gop",
			"format_settings__matrix",
			"format_settings__picture_structure",
			"format_settings__qpel",
			"format_settings__reference_frames",
			"format_settings_matrix_data",
			"format_version",
			"frame_count",
			"frame_rate",
			"frame_rate_mode",
			"framecount_source",
			"framerate_den",
			"framerate_mode_original",
			"framerate_num",
			"framerate_original_den",
			"framerate_original_num",
			"fromstats_bitrate",
			"fromstats_duration",
			"fromstats_framecount",
			"fromstats_streamsize",
			"gop__open_closed",
			"gop__open_closed_of_first_frame",
			"hdr_format",
			"hdr_format_commercial",
			"height",
			"height_offset",
			"id_in_the_original_source_medium",
			"internet_media_type",
			"intra_dc_precision",
			"irisfnumber",
			"language",
			"mastering_display_color_primaries",
			"mastering_display_luminance",
			"masteringdisplay_colorprimaries_source",
			"masteringdisplay_luminance_source",
			"matrix_coefficients",
			"matrix_coefficients_original",
			"matrix_coefficients_original_source",
			"matrix_coefficients_source",
			"maxcll_source",
			"maxfall_source",
			"maximum_bit_rate",
			"maximum_content_light_level",
			"maximum_frame_rate",
			"maximum_frameaverage_light_level",
			"mdhd_duration",
			"minimum_frame_rate",
			"muxing_mode",
			"nominal_bit_rate",
			"nominal_frame_rate",
			"numberofframes",
			"original_display_aspect_ratio",
			"original_frame_rate",
			"original_height",
			"original_pixel_aspect_ratio",
			"original_scan_order",
			"original_scan_type",
			"original_source_medium",
			"original_width",
			"pixel_aspect_ratio",
			"rotation",
			"sampled_height",
			"sampled_width",
			"scan_order",
			"scan_type",
			"scan_type__store_method",
			"source_delay",
			"source_delay_source",
			"source_duration",
			"source_duration_firstframe",
			"source_duration_lastframe",
			"source_frame_count",
			"source_stream_size",
			"standard",
			"statistics_tags_issue",
			"stored_height",
			"stored_width",
			"stream_size",
			"tagged_date",
			"time_code_of_first_frame",
			"time_code_source",
			"title",
			"track_position",
			"transfer_characteristics",
			"transfer_characteristics_original",
			"transfer_characteristics_original_source",
			"transfer_characteristics_source",
			"unique_id",
			"videoorientation",
			"width",
			"width_offset",
			"writing_library"
		]
	}
}
